pymotivaxmc2/__init__.py
pymotivaxmc2/cli.py
pymotivaxmc2/controller.py
pymotivaxmc2/enums.py
pymotivaxmc2/exceptions.py
pymotivaxmc2/core/__init__.py
pymotivaxmc2/core/discovery.py
pymotivaxmc2/core/dispatcher.py
pymotivaxmc2/core/logging.py
pymotivaxmc2/core/protocol.py
pymotivaxmc2/core/socket_mgr.py
pymotivaxmc2/core/xmlcodec.py
pymotivaxmc2-0.6.7.dist-info/licenses/LICENSE
pymotivaxmc2-0.6.7.dist-info/METADATA
pymotivaxmc2-0.6.7.dist-info/WHEEL
pymotivaxmc2-0.6.7.dist-info/entry_points.txt
pymotivaxmc2-0.6.7.dist-info/top_level.txt
pymotivaxmc2-0.6.7.dist-info/RECORD
