Metadata-Version: 2.4
Name: pymotivaxmc2
Version: 0.6.7
Summary: Async Python library for Emotiva XMC-2 and related devices
Author: eMotiva Integration
License: MIT
Project-URL: Homepage, https://github.com/yourusername/pymotivaxmc2
Project-URL: Documentation, https://pymotivaxmc2.readthedocs.io/
Project-URL: Repository, https://github.com/yourusername/pymotivaxmc2.git
Project-URL: Issues, https://github.com/yourusername/pymotivaxmc2/issues
Keywords: emotiva,xmc-2,avr,home-automation,async
Classifier: Development Status :: 4 - Beta
Classifier: Intended Audience :: Developers
Classifier: License :: OSI Approved :: MIT License
Classifier: Programming Language :: Python :: 3
Classifier: Programming Language :: Python :: 3.11
Classifier: Programming Language :: Python :: 3.12
Classifier: Topic :: Home Automation
Classifier: Topic :: Software Development :: Libraries :: Python Modules
Requires-Python: >=3.11
License-File: LICENSE
Requires-Dist: typing-extensions>=3.7.4
Dynamic: license-file
